{
    "1 article": "1 articolo",
    "10 articles": "10 articoli",
    "100 signes": "100 segni",
    "12 articles": "12 articoli",
    "2 articles": "2 articoli",
    "250 signes": "250 segni",
    "4 articles": "4 articoli",
    "500 signes": "500 segni",
    "6 articles": "6 articoli",
    "750 signes": "750 segni",
    "8 articles": "8 articoli",
    "Administrateur": "Amministratore",
    "Approbation par un modérateur": "Approvazione da parte di un moderatore",
    "Approuver le commentaire ?": "Approvare il commento?",
    "Approuvé": "Approvato",
    "Article complet en pleine page": "Articolo completo in tutta la pagina",
    "Article supprimé": "Articolo cancellato",
    "Articles par page": "Articoli per pagina",
    "Aucun article": "Nessun articolo",
    "Aucun commentaire": "Nessun commento",
    "Auteur": "Auteur",
    "Brouillon": "Progetto di copia",
    "Caractères par commentaire": "Personaggi per commento",
    "Choix du nombre maximum de caractères pour chaque commentaire de l'article, mise en forme html comprise.": "Scegliere il numero massimo di caratteri per ciascun commento dell'articolo, la formattazione HTML inclusa.",
    "Commentaire approuvé": "Commento approvato",
    "Commentaire rejeté": "Commento respinto",
    "Commentaire supprimé": "Commento cancellato",
    "Commentaires": "Commenti",
    "Commentaires supprimés": "Commenti cancellati",
    "Date de publication": "Data di pubblicazione",
    "Edition - Suppression": "Edizione - soppressione",
    "Effacer l'article": "Cancella l'articolo",
    "Fermer les commentaires": "Disattiva i commenti",
    "Gestion des commentaires": "Gestione dei commenti",
    "Grande": "Grande",
    "Groupe du propriétaire": "Gruppo del proprietario",
    "Image de couverture": "Copertura",
    "Informations générales": "Informazioni generali",
    "L'article n'est visible qu'après la date de publication prévue.": "L'articolo è visibile solo dopo la data di pubblicazione fornita.",
    "Largeur de l'image": "Larghezza dell'immagine",
    "Le texte de l'article est adapté autour de l'image": "Il testo dell'articolo è adattato all'immagine",
    "Les utilisateurs des groupes supérieurs accèdent à l'article sans restriction": "Gli utenti di gruppi più alti accedono all'articolo senza restrizioni",
    "Lien du flux RSS": "Lien Du Flux RSS",
    "Masquer l'image dans l'article": "Nascondi l'immagine nell'articolo",
    "Masquer l'image de couverture dans l'article": "Nascondi l'immagine di copertina nell'articolo",
    "Membre": "Membro",
    "Notification par email": "Email di notifica par",
    "Nouvel article créé": "Nuovo articolo creato",
    "Options de publication": "Opzioni di pubblicazione",
    "Permalink": "Permalink",
    "Petite": "Petite",
    "Pleine largeur": "Intera larghezza",
    "Propriétaire": "Proprietario",
    "Publier": "Pubblicare",
    "Rejeter le commentaire ?": "Rifiutare il commento?",
    "Rejeté": "Respinto",
    "Rédiger un article": "Scrivi un articolo",
    "Supprimer cet article ?": "Elimina questo articolo?",
    "Supprimer le commentaire ?": "Elimina il commento?",
    "Supprimer tous les commentaire ?": "Elimina tutti i commenti?",
    "Tableau : couverture + 200 signes": "Tabella: copertina + 200 segni",
    "Tableau : couverture + 400 signes": "Tabella: copertina + 400 segni",
    "Tableau : couverture + 600 signes": "Tabella: copertina + 600 segni",
    "Tableau : couverture + 800 signes": "Tabella: copertina + 800 segni",
    "Taille optimale de l'image de couverture : 920 x 350 pixels.": "Dimensione ottimale dell'immagine di copertina: 920 x 350 pixel.",
    "Texte de l'étiquette": "Testo dell'etichetta",
    "Tous les groupes": "Tutti i gruppi",
    "Tout effacer": "Cancellare tutto",
    "Très Grande": "Molto alto",
    "Très petite": "Molto piccolo",
    "À droite ": "A destra",
    "À gauche": "A sinistra",
    "Éditer  / Approuver les commentaires": "Modifica / approva i commenti",
    "Éditer l'article": "Modifica l'articolo",
    "Éditeur": "Editore",
    "État": "État"
}