{
    "A tous les groupes depuis": "Şu tarihten itibaren tüm gruplara",
    "A un membre": "Bir üyeye",
    "A une Adresse électronique": "Bir E-posta Adresine",
    "Alignement du formulaire": "Form Hizalama",
    "Aucune donnée": "Veri yok",
    "Aucune donnée à effacer": "Silinecek veri yok",
    "Aucune donnée à exporter": "Dışa aktarılacak veri yok",
    "Aucune option pour une étiquette": "Etiket seçeneği yok",
    "Captcha incorrect": "Yanlış Captcha",
    "Case à cocher": "Onay kutusu",
    "Champ obligatoire": "Gerekli alan",
    "Champ texte": "Metin alanı",
    "Courriel": "E-posta",
    "Deux colonnes": "İki sütun",
    "Dix colonnes": "On sütun",
    "Données effacées": "Veriler silindi",
    "Douze colonnes": "On iki sütun",
    "Décalage à gauche": "Sola kaydirma",
    "Effacer toutes les données": "Tüm verileri temizle",
    "Envoyer": "Göndermek",
    "Export des données": "Verileri dışa aktarma",
    "Exporter toutes les données": "Tüm verileri dışa aktar",
    "Formulaire soumis": "Form gönderildi",
    "Gabarit": "Şablon",
    "Grand champ texte": "Geniş metin alanı",
    "Huit colonnes": "Sekiz sütun",
    "Largeur du logo": "Logo genişliği",
    "Le formulaire ne contient aucun champ.": "Form herhangi bir alan içermiyor.",
    "Liste des champs": "Alanların listesi",
    "Logo du site": "Site logosu",
    "Neuf colonnes": "Dokuz sütun",
    "Nom du site": "Sitenin adı",
    "Onze colonnes": "On bir sütun",
    "Options de configuration": "Yapılandırma seçenekleri",
    "Page du site": "Site sayfası",
    "Redirection après soumission du formulaire": "Form gönderiminden sonra yönlendirme",
    "Sept colonnes": "Yedi sütun",
    "Six colonnes": "Altı sütun",
    "Sujet du mail": "Posta konusu",
    "Supprimer cet enregistrement ?": "Bu kayıt silinsin mi?",
    "Supprimer tous les enregistrements ?": "Tüm kayıtlar silinsin mi?",
    "Sélection": "Seçim",
    "Sélectionnez au moins un groupe, un utilisateur ou saisissez un email. Votre serveur doit autoriser les envois de mail.": "En az bir grup, bir kullanıcı seçin veya bir e-posta girin. Sunucunuz posta göndermeye izin vermelidir.",
    "Type de signature": "İmza türü",
    "Une colonne": "Bir sütun",
    "Validation du formulaire": "Form doğrulama",
    "Vide affiche le texte par défaut": "Boş ise, varsayılan metni görüntüler",
    "Voir et exporter les données du formulaire": "Form verilerini görüntüle ve dışa aktar",
    "Étiquette": "Etiket",
    "Étiquette du bouton de soumission": "Düğme etiketini gönder"
}